taskcluster_urls/__init__.py
taskcluster_urls-13.0.2.dist-info/licenses/LICENSE
taskcluster_urls-13.0.2.dist-info/METADATA
taskcluster_urls-13.0.2.dist-info/WHEEL
taskcluster_urls-13.0.2.dist-info/top_level.txt
taskcluster_urls-13.0.2.dist-info/RECORD
