Metadata-Version: 2.4
Name: taskcluster-urls
Version: 13.0.2
Summary: Standardized url generator for taskcluster resources.
Home-page: https://github.com/taskcluster/taskcluster-lib-urls
Author: Brian Stack
Author-email: bstack@mozilla.com
License: MPL2
Classifier: License :: OSI Approved :: Mozilla Public License 2.0 (MPL 2.0)
Classifier: Programming Language :: Python :: 2
Classifier: Programming Language :: Python :: 2.7
Classifier: Programming Language :: Python :: 3
Classifier: Programming Language :: Python :: 3.5
Classifier: Programming Language :: Python :: 3.6
License-File: LICENSE
Dynamic: author
Dynamic: author-email
Dynamic: classifier
Dynamic: description
Dynamic: description-content-type
Dynamic: home-page
Dynamic: license
Dynamic: license-file
Dynamic: summary
